neuralknight/__init__.py
neuralknight/routes.py
neuralknight/security.py
neuralknight/models/__init__.py
neuralknight/models/accumulating_iter.py
neuralknight/models/agent.py
neuralknight/models/base_agent.py
neuralknight/models/base_board.py
neuralknight/models/board.py
neuralknight/models/board_constants.py
neuralknight/models/board_model.py
neuralknight/models/meta.py
neuralknight/models/table_ass.py
neuralknight/models/table_board.py
neuralknight/models/table_game.py
neuralknight/models/user_agent.py
neuralknight/scripts/__init__.py
neuralknight/scripts/bench.py
neuralknight/scripts/cli.py
neuralknight/scripts/initializedb.py
neuralknight/static/pyramid-16x16.png
neuralknight/static/pyramid.png
neuralknight/static/reset.css
neuralknight/static/style.css
neuralknight/templates/404.jinja2
neuralknight/templates/base.jinja2
neuralknight/tests/__init__.py
neuralknight/tests/conftest.py
neuralknight/tests/test_accumulating_iter.py
neuralknight/tests/test_agent_view.py
neuralknight/tests/test_board.py
neuralknight/tests/test_board_view.py
neuralknight/tests/test_mock_agent_integration.py
neuralknight/tests/test_mock_board_integration.py
neuralknight/tests/test_view_nofound.py
neuralknight/views/__init__.py
neuralknight/views/agent.py
neuralknight/views/agent_view.py
neuralknight/views/games.py
neuralknight/views/home.py
neuralknight/views/notfound.py
neuralknight-1.0.2.dist-info/METADATA
neuralknight-1.0.2.dist-info/RECORD
neuralknight-1.0.2.dist-info/WHEEL
neuralknight-1.0.2.dist-info/entry_points.txt
neuralknight-1.0.2.dist-info/top_level.txt
