Metadata-Version: 2.1
Name: neuralknight
Version: 1.0.2
Summary: A Chess-playing AI
Home-page: https://www.github.com/dsnowb/neuralknight
Author: David Snowberger, Shannon Tully, and Adam Grandquist
Author-email: david.snowberger@fartherout.org
License: MIT
Keywords: chess entertainment game ai
Platform: UNKNOWN
Classifier: Development Status :: 3 - Alpha
Classifier: Intended Audience :: Developers
Classifier: Topic :: Games/Entertainment :: Board Games
Classifier: Programming Language :: Python :: 3
Classifier: Operating System :: OS Independent
Classifier: Natural Language :: English
Classifier: License :: Freely Distributable
Classifier: Framework :: Pyramid
Classifier: Environment :: Console
Requires-Python: >=3.6
Provides-Extra: dev
Provides-Extra: testing
Requires-Dist: requests
Provides-Extra: dev
Requires-Dist: cornice; extra == 'dev'
Requires-Dist: plaster-pastedeploy; extra == 'dev'
Requires-Dist: psycopg2-binary; extra == 'dev'
Requires-Dist: pyramid (>=1.9a); extra == 'dev'
Requires-Dist: pyramid-debugtoolbar; extra == 'dev'
Requires-Dist: pyramid-jinja2; extra == 'dev'
Requires-Dist: pyramid-retry; extra == 'dev'
Requires-Dist: pyramid-tm; extra == 'dev'
Requires-Dist: pytest; extra == 'dev'
Requires-Dist: pytest-cov; extra == 'dev'
Requires-Dist: requests; extra == 'dev'
Requires-Dist: SQLAlchemy; extra == 'dev'
Requires-Dist: transaction; extra == 'dev'
Requires-Dist: zope.sqlalchemy; extra == 'dev'
Requires-Dist: waitress; extra == 'dev'
Provides-Extra: testing
Requires-Dist: WebTest (>=1.3.1); extra == 'testing'
Requires-Dist: pytest; extra == 'testing'
Requires-Dist: pytest-cov; extra == 'testing'
Requires-Dist: requests; extra == 'testing'
